jogo_rpg/__init__.py
jogo_rpg/batalha.py
jogo_rpg/npc.py
jogo_rpg/player.py
jogo_rpg/utils.py
jogo_rpg-0.1.dist-info/METADATA
jogo_rpg-0.1.dist-info/WHEEL
jogo_rpg-0.1.dist-info/top_level.txt
jogo_rpg-0.1.dist-info/RECORD
