Metadata-Version: 2.1
Name: jogo-rpg
Version: 0.1
Summary: Um jogo RPG simples em Python
Home-page: https://github.com/macauli10/JogoDeRPG
Author: Macauli Missouri
Author-email: macaulimissouri0@gmail.com
